Workbook

Sheet Invoice
G4: Invoice No.: | H4: F16-260728 F16-260803
G5: Date: | H5: 46261
E7: COMMERCIAL INVOICE
B9: Buyer | F9: Seller
B10: Fuse Energy CO.,LTD | F10: SUNKEAN ENERGY CO., LTD.
B11: Unit 3 Fuse Energy, Here East 3-4 E Bay Ln London, E20 3BS | F11: Building A, No. 2 South Changjiang Road, Xinwu District, Wuxi, Jiangsu, China
B12: Contact：Mikita Kryvitski | F12: Contact: Angela
B13: Tel: +44 7876 251937 | F13: Tel: +86 (510)81083036
B16: Marks | C16: No. | D16: Description | E16: Item No. | F16: Qty | G16: Unit Price | H16: Line Total
B17: MADE IN CHINA P/NO.: 1-1 | C17: 1 | D17: Wiring Harness | E17: BY000201 3M DC Harness | F17: 50 | G17: 6.1 | H17: =F17*G17 -> 305 | J17: =F17*3 -> 150
C18: 2 | E18: BY000202 5M DC Harness | F18: 50 | G18: 8.2 | H18: =F18*G18 -> 410 | J18: =+F18*5 -> 250
C19: 3 | E19: BY000203 10M DC Harness | F19: 50 | G19: 13.36 | H19: =F19*G19 -> 668 | J19: =F19*10 -> 500
C20: 1 | D20: Wiring Harness | E20: BY000201 3M DC Harness | F20: 87 | G20: 3.621 | H20: =F20*G20 -> 315.027 | J20: =F20*3 -> 261
C21: 2 | E21: BY000202 5M DC Harness | F21: 33 | G21: 5.72 | H21: =F21*G21 -> 188.76 | J21: =+F21*5 -> 165
C22: 3 | E22: BY000203 10M DC Harness | F22: 10 | G22: 10.87 | H22: =F22*G22 -> 108.7 | J22: =F22*10 -> 100
F23: DAP Air Shipping cost(USD) | H23: 2400
F24: Total Amount (USD) | H24: =SUM(H17:H23) -> 4395.487
B26: Remarks:
B27: Origin： | C27: Made in China
B28: Delivery term： | C28: DAP
B29: Destination：
B30: Shipping Method: | C30: By AIR
A46: COPYRIGHT @ 2024 SUNKEAN

Sheet Packing List
H4: Invoice No.: | I4: F16-260728 F16-260803
H5: Date: | I5: =Invoice!H5 -> 46261
B7: PACKING LIST
B9: Buyer | G9: Seller
B10: =Invoice!B10 -> Fuse Energy CO.,LTD | G10: =Invoice!F10 -> SUNKEAN ENERGY CO., LTD.
B11: =Invoice!B11 -> Unit 3 Fuse Energy, Here East 3-4 E Bay Ln London, E20 3BS | G11: =Invoice!F11 -> Building A, No. 2 South Changjiang Road, Xinwu District, Wuxi, Jiangsu, China
B12: =Invoice!B12 -> Contact：Mikita Kryvitski | G12: =Invoice!F12 -> Contact: Angela
B13: =Invoice!B13 -> Tel: +44 7876 251937 | G13: =Invoice!F13 -> Tel: +86 (510)81083036
B15: Marks | C15: No. | D15: Description | E15: Item No. | F15: Qty (m) | G15: Net Weight (kg) | H15: Gross Weight (kg) | I15: Meas (CBM)
B16: =Invoice!B17 -> MADE IN CHINA P/NO.: 1-1 | C16: 1 | D16: Wiring Harness | E16: BY000201 3M DC Harness | F16: 50 | G16: =F16*K16 -> 17 | H16: 202.71 | I16: 1.1808 | K16: 0.34
C17: 2 | E17: BY000202 5M DC Harness | F17: 50 | G17: =F17*K17 -> 25.5 | K17: 0.51
C18: 3 | E18: BY000203 10M DC Harness | F18: 50 | G18: =F18*K18 -> 46.5 | K18: 0.93
C19: 4 | D19: Wiring Harness | E19: BY000201 3M DC Harness | F19: 87 | G19: =F19*K19 -> 29.58 | K19: 0.34
C20: 5 | E20: BY000202 5M DC Harness | F20: 33 | G20: =F20*K20 -> 16.83 | K20: 0.51
C21: 6 | E21: BY000203 10M DC Harness | F21: 10 | G21: =F21*K21 -> 9.3 | K21: 0.93
D22: Total Amount | F22: =SUM(F16:F21) -> 280 | G22: =SUM(G16:G21) -> 144.71 | H22: =H16 -> 202.71 | I22: =I16 -> 1.1808
B24: Remarks:
B25: Origin： | C25: Made in China
B26: G.W.： | C26: =H22 -> 202.71 | D26: kg
B27: Packed In | C27: 1 | D27: Pallet
B41: =Invoice!A46 -> COPYRIGHT @ 2024 SUNKEAN

Sheet 报关单
A1: 中华人民共和国海关出口货物报关单
A2: 预录入编号： 海关编号： 页码/页数：
A3: 境内发货人 | B3: （91320214MAE7K1E69B） | D3: 出境关别 | G3: 出口日期 | I3: 申报日期 | J3: 备案号
A4: 三钧能源（无锡）有限公司
A5: 境外收货人 | D5: 运输方式 | G5: 运输工具名称及航次号 | I5: 提运单号
A6: =Invoice!B10 -> Fuse Energy CO.,LTD | D6: 空运
A7: 生产销售单位 | B7: （91320214MAE7K1E69B） | D7: 监管方式 | G7: 征免性质 | I7: 许可证号
A8: 三钧能源（无锡）有限公司 | D8: 一般贸易 | G8: 一般征税
A9: 合同协议号 | D9: 贸易国（地区） | G9: 运抵国（地区） | I9: 指运港 | J9: 离境口岸
A10: =Invoice!H4 -> F16-260728 F16-260803 | D10: 英国 | G10: 英国
A11: 包装种类 | D11: 件数 | E11: 毛重（千克） | G11: 净重(千克） | H11: 成交方式 | I11: 运费 | J11: 保费 | K11: 杂费
A12: 再生木托 | D12: ='Packing List'!C27 -> 1 | E12: ='Packing List'!H22 -> 202.71 | G12: ='Packing List'!G22 -> 144.71 | H12: DAP | I12: 1375 | J12: 5
A13: 随附单证及编号
A14: 标记唛码及备注
A15: =Invoice!B17 -> MADE IN CHINA P/NO.: 1-1
A17: 项号 | B17: 商品编号 | C17: 商品名称及规格型号 | E17: 数量及单位 | G17: 单价/总价/币制 | H17: 原产国（地区） | I17: 最终目的国（地区） | J17: 境内货源地 | K17: 征免
A18: 1 | B18: 8544601290 | C18: 线束 | E18: 280 1426 | F18: 套 | G18: 4395.487 | H18: 中国 | I18: =G10 -> 英国 | J18: 无锡其他
G19: USD
E20: TOTAL: | G20: =Invoice!H24+#REF! -> #REF!
C21: 特殊关系确认：否 | E21: 价格影响确认：否 | G21: 支付特许权使用费确认：否 | I21: 自报自缴：否
A22: 申报人员 | C22: 申报人员证号 | D22: 电话 | E22: 兹申明对以上内容承担如实申报、依法纳税之法律责任 | I22: 海关批注及签章
A23: 申报单位 | E23: 申报单位（签章）

Sheet 申报要素
A1: 品名：线束
A2: 英文：wiring harness
A3: HS： 8544601290
A4: 额定电压：2000V
A5: 型号：无型号
A6: 结构类型：XLPE绝缘材料+铜+连接器(有接头)+保险丝
A7: 用途：机械用，连接用
A8: 无品牌，不享惠
